AUTHORS
CHANGES
LICENSE
MANIFEST.in
README.rst
TODO
requirements-setup.txt
requirements-sphinx.txt
requirements.py
setup.cfg
setup.py
PyCPUID.egg-info/PKG-INFO
PyCPUID.egg-info/SOURCES.txt
PyCPUID.egg-info/dependency_links.txt
PyCPUID.egg-info/not-zip-safe
PyCPUID.egg-info/requires.txt
PyCPUID.egg-info/top_level.txt
doc/Makefile
doc/make.bat
doc/source/Authors.rst
doc/source/Changes.rst
doc/source/Introduction.rst
doc/source/TODO.rst
doc/source/conf.py
doc/source/favicon.ico
doc/source/fds-icon.png
doc/source/index.rst
doc/source/modules.rst
doc/source/pycpuid.rst
pycpuid/__init__.py
pycpuid/_pycpuid.c
pycpuid/pycpuid.py