Metadata-Version: 1.0
Name: PyCPUID
Version: 0.4
Summary: CPUID powered by Python.
Home-page: http://pypi.python.org/pypi/PyCPUID
Author: Flight Data Services Ltd
Author-email: developers@flightdataservices.com
License: GNU Library or Lesser General Public License (LGPL)
Download-URL: https://github.com/FlightDataServices/PyCPUID
Keywords: cpuid
Platform: OS Independent
Classifier: Development Status :: 4 - Beta
Classifier: Environment :: Console
Classifier: Intended Audience :: Developers
Classifier: License :: OSI Approved :: GNU Library or Lesser General Public License (LGPL)
Classifier: Programming Language :: Python :: 2.5
Classifier: Programming Language :: Python :: 2.6
Classifier: Programming Language :: Python :: 2.7
Classifier: Programming Language :: Python :: Implementation :: CPython
Classifier: Operating System :: OS Independent
Classifier: Topic :: Software Development
